LICENSE.txt
README.md
setup.cfg
setup.py
sec_python.egg-info/PKG-INFO
sec_python.egg-info/SOURCES.txt
sec_python.egg-info/dependency_links.txt
sec_python.egg-info/requires.txt
sec_python.egg-info/top_level.txt
secpy/__init__.py
secpy/company_concept.py
secpy/company_facts.py
secpy/frames.py
secpy/secpy_client.py
secpy/submissions.py
secpy/core/__init__.py
secpy/core/bulk_data.py
secpy/core/endpoint_enum.py
secpy/core/network_client.py
secpy/core/ticker_company_exchange_map.py
secpy/core/mixins/__init__.py
secpy/core/mixins/base_data_object_mixin.py
secpy/core/mixins/base_endpoint_mixin.py
secpy/core/mixins/base_network_client_mixin.py
secpy/core/utils/__init__.py
secpy/core/utils/cik_opts.py
secpy/core/utils/period_format_opts.py
tests/__init__.py
tests/secpy/__init__.py
tests/secpy/core/__init__.py
tests/secpy/core/bulk_data_test.py
tests/secpy/core/endpoint_enum_test.py
tests/secpy/core/ticker_company_exchange_map_test.py
tests/secpy/core/utils/__init__.py
tests/secpy/core/utils/cik_opts_test.py
tests/secpy/core/utils/period_format_opts_test.py
tests/testutils/__init__.py
tests/testutils/mock_utils.py