Metadata-Version: 2.1
Name: sec-python
Version: 0.4.0a0
Summary: Python library for interacting w/ the SEC REST API: https://www.sec.gov/edgar/sec-api-documentation
Home-page: https://github.com/McKalvan/secpy
Author: Calvin Kessler
License: MIT
Download-URL: https://github.com/McKalvan/secpy/archive/refs/tags/v0.4.0-alpha.zip
Keywords: SEC,EDGAR,finance,REST API wrapper
Platform: UNKNOWN
Classifier: Development Status :: 3 - Alpha
Classifier: Intended Audience :: Developers
Classifier: License :: OSI Approved :: MIT License
Classifier: Programming Language :: Python :: 3
License-File: LICENSE.txt
